LICENSE
MANIFEST.in
README.rst
setup.py
examples/async_task/app.py
examples/async_task/index.plim
examples/async_task/main.pyj
examples/async_task/styles.styl
examples/async_task/__pycache__/app.cpython-35.pyc
examples/async_task/__pycache__/main.cpython-35.pyc
examples/error_messages/app.py
examples/error_messages/index.plim
examples/error_messages/main.pyj
examples/error_messages/rapydscript.plim
examples/error_messages/styles.styl
examples/error_messages/stylus.plim
examples/error_messages/__pycache__/app.cpython-35.pyc
examples/sync_task/app.py
examples/sync_task/index.plim
examples/sync_task/main.pyj
examples/sync_task/styles.styl
examples/sync_task/__pycache__/app.cpython-35.pyc
examples/sync_task/__pycache__/main.cpython-35.pyc
examples/websocket_task/app.py
examples/websocket_task/index.plim
examples/websocket_task/main.pyj
examples/websocket_task/styles.styl
examples/websocket_task/__pycache__/app.cpython-35.pyc
examples/websocket_task/__pycache__/main.cpython-35.pyc
muffin_playground/__init__.py
muffin_playground/watcher.py
muffin_playground.egg-info/PKG-INFO
muffin_playground.egg-info/SOURCES.txt
muffin_playground.egg-info/dependency_links.txt
muffin_playground.egg-info/requires.txt
muffin_playground.egg-info/top_level.txt
muffin_playground/__pycache__/__init__.cpython-35.pyc
muffin_playground/__pycache__/watcher.cpython-35.pyc
muffin_playground/resources/boilerplate.plim
muffin_playground/resources/debug.js
muffin_playground/resources/jquery-3.1.0.min.js
muffin_playground/resources/wsclient.pyj
muffin_playground/resources/css/bootstrap-3.3.7.min.css
muffin_playground/resources/fonts/glyphicons-halflings-regular.ttf
muffin_playground/resources/fonts/glyphicons-halflings-regular.woff
muffin_playground/resources/fonts/glyphicons-halflings-regular.woff2
muffin_playground/resources/js/bootstrap-3.3.7.min.js