Metadata-Version: 1.1
Name: muffin-playground
Version: 0.0.11
Summary: Convenience classes for simple muffin apps
Home-page: https://github.com/feihong/muffin-playground
Author: Feihong Hsu
Author-email: feihong.hsu@gmail.com
License: Apache 2.0
Keywords: asyncio,aiohttp,muffin
Platform: Any
Classifier: Development Status :: 3 - Alpha
Classifier: Intended Audience :: Developers
Classifier: Natural Language :: English
Classifier: License :: OSI Approved :: Apache Software License
Classifier: Programming Language :: Python
Classifier: Programming Language :: Python :: 3
Classifier: Programming Language :: Python :: 3.5
Classifier: Programming Language :: Python :: Implementation :: CPython
Classifier: Programming Language :: Python :: Implementation :: PyPy
